scaflog_zoho_mcp_server/__init__.py
scaflog_zoho_mcp_server/auth.py
scaflog_zoho_mcp_server/config.py
scaflog_zoho_mcp_server/models.py
scaflog_zoho_mcp_server/resource_config.py
scaflog_zoho_mcp_server/server.py
scaflog_zoho_mcp_server/service.py
mseep_scaflog_zoho_mcp_server-0.1.2.dist-info/METADATA
mseep_scaflog_zoho_mcp_server-0.1.2.dist-info/WHEEL
mseep_scaflog_zoho_mcp_server-0.1.2.dist-info/entry_points.txt
mseep_scaflog_zoho_mcp_server-0.1.2.dist-info/RECORD
