Metadata-Version: 2.4
Name: mseep-scaflog-zoho-mcp-server
Version: 0.1.2
Summary: MCP Server for Zoho Creator Integration
Author-email: mseep <support@skydeck.ai>
Requires-Python: >=3.12
Requires-Dist: httpx>=0.24.0
Requires-Dist: mcp>=1.1.0
Requires-Dist: pydantic>=2.0.0
Requires-Dist: python-dotenv>=1.0.0
Requires-Dist: typing-extensions>=4.7.0
Requires-Dist: zcrmsdk==3.1.0
Provides-Extra: test
Requires-Dist: pytest-asyncio>=0.21.0; extra == 'test'
Requires-Dist: pytest-cov>=4.1.0; extra == 'test'
Requires-Dist: pytest>=7.0.0; extra == 'test'
